{"classes":["DRUG","ALCOHOL","VIOLENCE","SEX","THEFT","FAMILY","MINOR","VEHICULAR","KIDNAP","MISCONDUCT","FRAUD","WEAPON","TRESPASS","COURT OFFENSE","POLICE OFFENSE","FINANCIAL","LICENSE"],"annotations":[["BAD CK $150+NSF/NO ACCT",{"entities":[[0,23,"FINANCIAL"]]}],["FALSE STATEMENTS",{"entities":[[0,16,"COURT OFFENSE"]]}],["EVADE ARREST",{"entities":[[0,12,"POLICE OFFENSE"]]}],["IDENTITY THEFT FRAUD WHEN USING/POSSESSI",{"entities":[[0,40,"FRAUD"]]}],["DEF TRES POSTED",{"entities":[[0,15,"TRESPASS"]]}],["Firearm Discharge under the Influence",{"entities":[[0,37,"WEAPON"]]}],["TAMPER/FABRICATE PHYSICAL EVID",{"entities":[[0,30,"COURT OFFENSE"]]}],["VOP",{"entities":[[0,3,"COURT OFFENSE"]]}],["CONSPIRACY - DEFRAUDING HOTELS/MOTELS +GT;$200",{"entities":[[0,46,"FRAUD"]]}],["\"FUGITIVE, FELONY W/O WARRANT\"",{"entities":[[1,29,"POLICE OFFENSE"]]}],["CARRYING CONCEALED WEAPON",{"entities":[[0,25,"WEAPON"]]}],["USE FIREARM IN FELONY 1ST OFF",{"entities":[[0,29,"WEAPON"]]}],["2. CONCEALED WEAPON",{"entities":[[0,19,"WEAPON"]]}],["FRAUD USE CREDIT/DEBIT CARD",{"entities":[[0,27,"FRAUD"]]}],["FAIL TO BE BOOKED(STATE CITATION)",{"entities":[[0,33,"POLICE OFFENSE"]]}],["FUGITIVE",{"entities":[[0,8,"POLICE OFFENSE"]]}],["FAILURE TO APPEAR TRAFFIC",{"entities":[[0,25,"COURT OFFENSE"]]}],["CONTEMPT OF FAMILY COURT BY ADULTOFFENSE",{"entities":[[0,40,"COURT OFFENSE"]]}],["FAIL TO APPEAR",{"entities":[[0,14,"COURT OFFENSE"]]}],["DEADLY WEAPON-INT INJURE",{"entities":[[0,24,"WEAPON"]]}],["OPERATE VEHICLE ON HIGHWAY WITHOUT A VALID LICENSE - 2ND OFFENSE",{"entities":[[27,50,"LICENSE"]]}],["AGG ASSAULT W/DEADLY WEAPON",{"entities":[[0,27,"WEAPON"]]}],["Municipal Court Appeal",{"entities":[[0,22,"COURT OFFENSE"]]}],["PROPERTY",{"entities":[[0,8,"TRESPASS"]]}],["CONTEMPT",{"entities":[[0,8,"COURT OFFENSE"]]}],["FAILURE TO APPEAR 2ND DEG",{"entities":[[0,25,"COURT OFFENSE"]]}],["RESIST OFFICER WO VIOL-INTIMIDATION",{"entities":[[0,35,"POLICE OFFENSE"]]}],["SHOOT MISSILES-DWELLING/VEH.",{"entities":[[0,27,"WEAPON"]]}],["FAIL TO PAY FINE",{"entities":[[0,16,"FINANCIAL"]]}],["DRIVE WITH LICENSE SUSPENDED/REVOKED/CANCELLED",{"entities":[[0,46,"LICENSE"]]}],["CRIMINAL TRESPASS",{"entities":[[0,17,"TRESPASS"]]}],["POSSESSION OF FIREARM BY FELON",{"entities":[[0,30,"WEAPON"]]}],["Fraud/Theft",{"entities":[[0,11,"FRAUD"]]}],["FUGITIVE",{"entities":[[0,8,"POLICE OFFENSE"]]}],["\"INTENTIONALLY CAUSE DAMAGE TO PROPERTY $400-$1,000\"",{"entities":[[1,51,"TRESPASS"]]}],["FAIL TO APPEAR FOR BOOKING/PROCESS",{"entities":[[0,34,"COURT OFFENSE"]]}],["Fraud/Theft",{"entities":[[0,11,"FRAUD"]]}],["TRESPASS",{"entities":[[0,8,"TRESPASS"]]}],["VIOLATE PROBATION/ COMM CONTRL",{"entities":[[0,30,"COURT OFFENSE"]]}],["RESISTING ARREST",{"entities":[[0,16,"POLICE OFFENSE"]]}],["Tampering 1",{"entities":[[0,11,"COURT OFFENSE"]]}],["PROPERTY",{"entities":[[0,8,"TRESPASS"]]}],["VIO BAIL BOND/CLASS 3 CONVIC",{"entities":[[0,28,"COURT OFFENSE"]]}],["PROH WEAPONS SWITCHBLADE/KNUCKLES",{"entities":[[0,33,"WEAPON"]]}],["WEAPONS - CARRYING CONCEALED",{"entities":[[0,28,"WEAPON"]]}],["RESIST ARREST SEARCH OR TRANSP",{"entities":[[0,30,"POLICE OFFENSE"]]}],["CRIMINAL CONTEMPT",{"entities":[[0,17,"COURT OFFENSE"]]}],["TOLL-FAILED TO PAY",{"entities":[[0,18,"FINANCIAL"]]}],["Fraud/Theft",{"entities":[[0,11,"FRAUD"]]}],["\"FORGERY LESS THAN $10,000\"",{"entities":[[1,26,"FRAUD"]]}],["TOLL/FAIL TO PAY/MID POINT BRIDGE - 2 AXLE",{"entities":[[0,42,"FINANCIAL"]]}],["DRIVING WITH SUSPENDED LICENSE",{"entities":[[0,30,"LICENSE"]]}],["ESCAPE - 2ND DEGREE",{"entities":[[0,19,"POLICE OFFENSE"]]}],["FEDERAL HOLD",{"entities":[[0,12,"COURT OFFENSE"]]}],["DIVERSION OF FUNDS \\u0026gt;$1000",{"entities":[[0,33,"FINANCIAL"]]}],["ESCAPE",{"entities":[[0,6,"POLICE OFFENSE"]]}],["PROB VIOLATION",{"entities":[[0,14,"COURT OFFENSE"]]}],["RESIST OFFICER OBSTRUCT WO VIOLENCE",{"entities":[[0,35,"POLICE OFFENSE"]]}],["PROPMALICIOUS DESTR",{"entities":[[0,19,"TRESPASS"]]}],["Fraud/Theft",{"entities":[[0,11,"FRAUD"]]}],["FAIL TO PAY TAX",{"entities":[[0,15,"FINANCIAL"]]}],["COURT COST",{"entities":[[0,10,"COURT OFFENSE"]]}],["VANDALISM 10",{"entities":[[0,12,"TRESPASS"]]}],["FAIL TO RPT NAME/ADDRESS CHG; DRIV LIC/REGISTRATN",{"entities":[[30,49,"LICENSE"]]}],["BREAKING + ENTERING A BUILDING WITH INTENT",{"entities":[[0,42,"TRESPASS"]]}],["OBSTRUCT PUBLIC OFFICER",{"entities":[[0,23,"POLICE OFFENSE"]]}],["ISSUE DISHONORED CHECK-VALUE NOT MORE THAN $250",{"entities":[[0,47,"FINANCIAL"]]}],["VIOLATION OF PROMISE TO APPEAR",{"entities":[[0,30,"COURT OFFENSE"]]}],["DRIVE WHILE LIC SUSP HABITUAL",{"entities":[[0,29,"LICENSE"]]}],["CRIMINAL TRESPASS REMAIN ON LAND",{"entities":[[0,32,"TRESPASS"]]}],["BREAKING + ENTERING A BUILDING WITH INTENT",{"entities":[[0,42,"TRESPASS"]]}],["Fraud/Theft",{"entities":[[0,11,"FRAUD"]]}],["HANDGUN ON PERSON: CARRY/WEAR",{"entities":[[0,29,"WEAPON"]]}],["CRIMINAL MISCHIEF",{"entities":[[0,17,"TRESPASS"]]}],["OBSTRUCTING OFFICER (OBS)",{"entities":[[0,25,"POLICE OFFENSE"]]}],["\"RESISTING/INTERFERING WITH ARREST, DETENTION OR STOP\"",{"entities":[[1,53,"POLICE OFFENSE"]]}],["DROVE WHILE UNLICENSED OR LICENSE NOT VALID",{"entities":[[0,43,"LICENSE"]]}],["FRAUD  (FALSE OWNER INFO PAWN ITEMS LESS THAN 300 DOLS)",{"entities":[[0,55,"FRAUD"]]}],["Fraud/Theft",{"entities":[[0,11,"FRAUD"]]}],["IDENTITY FRAUD",{"entities":[[0,14,"FRAUD"]]}],["FAILURE TO APPEAR (SMMS)",{"entities":[[0,24,"COURT OFFENSE"]]}],["PRESCR OBTAIN BY FRAUD",{"entities":[[0,22,"FRAUD"]]}],["FTA- FAILURE TO APPEAR WARRANT",{"entities":[[0,30,"COURT OFFENSE"]]}],["FAIL TO FILE TAXES",{"entities":[[0,18,"FINANCIAL"]]}],["LICENSE REQUIRED;REINSTATEMENT FEE",{"entities":[[0,34,"LICENSE"]]}],["PROBATION REVOKED (FELONY) AMENDED TO FIREARM-ALTER IDENTIFICATION (FELONY)",{"entities":[[0,17,"COURT OFFENSE"],[38,66,"WEAPON"]]}],["HOLD FOR EXTRADITION",{"entities":[[0,20,"COURT OFFENSE"]]}],["FRAUD - POSS DISPLAY BLANK FORGED STOLEN DR LIC OR ID",{"entities":[[0,53,"FRAUD"]]}],["VIOLATION OF PROB.",{"entities":[[0,17,"COURT OFFENSE"]]}],["WARRANT",{"entities":[[0,7,"COURT OFFENSE"]]}],["WEAPONS/UNLAWFUL POSSESSION:HANDGUNS /2",{"entities":[[0,39,"WEAPON"]]}],["DEF TRES POSTED",{"entities":[[0,15,"TRESPASS"]]}],["CHAUFFERS LICENSE PROHIBITED 4507-3",{"entities":[[0,35,"LICENSE"]]}],["PROPERTY",{"entities":[[0,8,"TRESPASS"]]}],["VIOLATION OF PROMISE TO APPEAR",{"entities":[[0,30,"COURT OFFENSE"]]}],["FS/CRIMINAL MISCHIEF",{"entities":[[0,20,"TRESPASS"]]}],["VIOLATIONS INVOLVING CHECKS AND DRAFTS",{"entities":[[0,38,"FINANCIAL"]]}],["RESIST/INTERFERE WITH ARREST",{"entities":[[0,28,"POLICE OFFENSE"]]}],["Protection Order Violation-criminal",{"entities":[[0,35,"COURT OFFENSE"]]}],["NO OPERATORS LICENSE",{"entities":[[0,20,"LICENSE"]]}],["ESCAPE - PRISON",{"entities":[[0,15,"POLICE OFFENSE"]]}],["FAIL TO APPEAR SUMMONS",{"entities":[[0,22,"COURT OFFENSE"]]}],["CONTEMPT OF COURT FOR FAILURE TO PAY FINES (FTP)",{"entities":[[0,48,"COURT OFFENSE"]]}],["ROGUE AND VAGABOND",{"entities":[[0,18,"TRESPASS"]]}],["POSS OF FIREARM DURING COMM OF FEL",{"entities":[[0,34,"WEAPON"]]}],["D/L NOT CARRIED/EXHIBITED",{"entities":[[0,25,"LICENSE"]]}],["NEGOTIATING WORTHLESS INSTRUMENT",{"entities":[[0,32,"FRAUD"]]}]]}