{"classes":["DRUG","ALCOHOL","VIOLENCE","SEX","THEFT","MINOR","VEHICULAR","KIDNAP","MISCONDUCT","FRAUD","WEAPON","TRESPASS","COURT OFFENSE","POLICE OFFENSE","FINANCIAL","LICENSE","ACCESSORY","ANIMAL","HARASSMENT"],"annotations":[["SIMPLE BATTERY\r",{"entities":[[0,14,"VIOLENCE"]]}],["ASSAULT-SEC DEGREE\r",{"entities":[[0,18,"VIOLENCE"]]}],["POLICE OFFICER - ASSAULT/RESIST/OBSTRUCT\r",{"entities":[[0,40,"VIOLENCE"]]}],["BATTERY\r",{"entities":[[0,7,"VIOLENCE"]]}],["Violence\r",{"entities":[[0,8,"VIOLENCE"]]}],["SIMPLE BATTERY\r",{"entities":[[0,14,"VIOLENCE"]]}],["DOMESTIC VIOLENCE\r",{"entities":[[0,17,"VIOLENCE"]]}],["AGGRAVATED ASSAULT\r",{"entities":[[0,18,"VIOLENCE"]]}],["ASSAULT/AGG=SIMPLE ASSLT ON LAW ENFOFF/3\r",{"entities":[[0,40,"VIOLENCE"]]}],["DEADLY CONDUCT\r",{"entities":[[0,14,"VIOLENCE"]]}],["ASSAULT OR BATTERY\r",{"entities":[[0,18,"VIOLENCE"]]}],["BATTERY\r",{"entities":[[0,7,"VIOLENCE"]]}],["BATTDOMSTRANGLE\r",{"entities":[[0,15,"VIOLENCE"]]}],["AGGRAV ASSAULT\r",{"entities":[[0,14,"VIOLENCE"]]}],["ASSAULT / ASSAULT \\u0026 BATTERY 3RD DEGREE\r",{"entities":[[0,43,"VIOLENCE"]]}],["TERRORISTIC THREATS-RECKLESS DISREGARD RISK\r",{"entities":[[0,43,"VIOLENCE"]]}],["FORCIBLE SODOMY\r",{"entities":[[0,15,"SEX"]]}],["ASSAULT FAMILY/HOUSEHOLD MEMBER PREV CONV IAT\r",{"entities":[[0,45,"VIOLENCE"]]}],["DOMESTIC BATTERING - FELONY - 3RD DEGREE\r",{"entities":[[0,40,"VIOLENCE"]]}],["FEL ASSAULT\r",{"entities":[[0,11,"VIOLENCE"]]}],["AGGRAVATED ROBBERY\r",{"entities":[[0,18,"VIOLENCE"]]}],["ASSAULT-SEC DEGREE\r",{"entities":[[0,18,"VIOLENCE"]]}],["HOMICIDE-MURDER\r",{"entities":[[0,15,"VIOLENCE"]]}],["AGGRAVATED ROBBERY\r",{"entities":[[0,18,"VIOLENCE"]]}],["DOMESTIC BATTERING - FELONY - 3RD DEGREE\r",{"entities":[[0,40,"VIOLENCE"]]}],["SEX ASSAULT 3 3 CTS\r",{"entities":[[0,19,"SEX"]]}],["ASSAULT WITH A DEADLY WEAPON\r",{"entities":[[0,7,"VIOLENCE"]]}],["DOMESTIC BATTERY 3RD DEGREE\r",{"entities":[[0,27,"VIOLENCE"]]}],["35-42-2-9(B) : STRANGULATION - DEF. APPL\r",{"entities":[[15,28,"VIOLENCE"]]}],["MISDEMEANOR - BATTERY\r",{"entities":[[0,21,"VIOLENCE"]]}],["DOC-SIMPLE ASSAULT.\r",{"entities":[[0,18,"VIOLENCE"]]}],["ASSAULT/AGG=SIMPLE ASSLT ON LAW ENFOFF/3\r",{"entities":[[0,40,"VIOLENCE"]]}],["DOMESTIC ASSAULT - 3RD DEGREE\r",{"entities":[[0,16,"VIOLENCE"]]}],["SEXUAL IMPOSITION\r",{"entities":[[0,17,"SEX"]]}],["AGGRAVATED SEXUAL BATTERY\r",{"entities":[[0,10,"VIOLENCE"],[11,17,"SEX"],[18,25,"VIOLENCE"]]}],["DOMESTIC ASSAULT-MISDEMEANOR-COMMITS ACT TO CAUSE FEAR OF IMMEDIATE BODILY HARM OR DEATH\r",{"entities":[[0,88,"VIOLENCE"]]}],["MURDER 2ND DEGREE; MURDER SECOND DEGREE DANGER/REPETIT/ENHANCE\r",{"entities":[[0,62,"VIOLENCE"]]}],["ASSAULT II\r",{"entities":[[0,10,"VIOLENCE"]]}],["CON-ARSON SECOND DEGREE\r",{"entities":[[0,23,"VIOLENCE"]]}],["SIMPLE BATTERY\r",{"entities":[[0,14,"VIOLENCE"]]}],["ASSAULT CAUSES BODILY INJURY FAMILY VIOLENCE\r",{"entities":[[0,44,"VIOLENCE"]]}],["ASSAULT \\C\\ FAMILY VIOLENCE\r",{"entities":[[0,27,"VIOLENCE"]]}],["DOM ASLT-MS-INFL ATTMPT BOD HRM-HANDS-UNKNOWN\r",{"entities":[[0,45,"VIOLENCE"]]}],["BATTERY\r",{"entities":[[0,7,"VIOLENCE"]]}],["INDECENT ASSAULT\r",{"entities":[[0,16,"SEX"]]}],["ASSAULT-SEC DEGREE\r",{"entities":[[0,18,"VIOLENCE"]]}],["FEL ASSAULT\r",{"entities":[[0,11,"VIOLENCE"]]}],["RECKLESS HOMICIDE\r",{"entities":[[0,17,"VIOLENCE"]]}],["ARMED ROBBERY WITH USE OF FORCE\r",{"entities":[[0,31,"VIOLENCE"]]}],["IMPLIED CONSENT\r",{"entities":[[0,15,"SEX"]]}],["CON-ARSON SECOND DEGREE\r",{"entities":[[0,23,"VIOLENCE"]]}],["INVOLUNTARY MANSLAUGHTER DUI OR DRUGS\r",{"entities":[[0,37,"VIOLENCE"]]}],["ASSAULT 4TH DEGREE\r",{"entities":[[0,18,"VIOLENCE"]]}],["DOMESTIC VIOLENCE 3RD-HARASSMENT\r",{"entities":[[0,32,"VIOLENCE"]]}],["COERCION WITH FORCE OR THREAT OF FORCE SEX MOTIVAT\r",{"entities":[[0,38,"VIOLENCE"],[39,50,"SEX"]]}],["ASSAULT CAUSES BODILY INJURY FAMILY VIOLENCE\r",{"entities":[[0,44,"VIOLENCE"]]}],["ASSAULT ON A FEMALE\r",{"entities":[[0,19,"VIOLENCE"]]}],["AMC8.30.120(A)(1)DISORDERLY CONDUCT-PUBLIC SEX\r",{"entities":[[17,46,"SEX"]]}],["FORCIBLE SODOMY\r",{"entities":[[0,15,"SEX"]]}],["INDECENT ASSAULT FORCIBLE COMPULSION\r",{"entities":[[0,36,"SEX"]]}],["AGGRAVATED MANSLAUGHTER /1\r",{"entities":[[0,26,"VIOLENCE"]]}],["AGG ASLT-THREAT-DDLY WPN\r",{"entities":[[0,24,"VIOLENCE"]]}],["DOMESTIC VIOLENCE 3RD-RECKLESS ENDANGER\r",{"entities":[[0,39,"VIOLENCE"]]}],["CRIMINAL SEXUAL CONDUCT-1ST DEGREE-PENETRATION - FEAR GREAT BODILY HARM\r",{"entities":[[0,71,"SEX"]]}],["ASSAULT/AGG=SIMPLE ASSLT ON LAW ENFOFF/3",{"entities":[[0,40,"VIOLENCE"]]}]]}